highrise/__init__.py
highrise/__main__.py
highrise/_unions.py
highrise/models.py
highrise/models_control.py
highrise/models_webapi.py
highrise/py.typed
highrise/webapi.py
highrise_bot_sdk-23.3.4.dist-info/METADATA
highrise_bot_sdk-23.3.4.dist-info/WHEEL
highrise_bot_sdk-23.3.4.dist-info/entry_points.txt
highrise_bot_sdk-23.3.4.dist-info/RECORD
