Metadata-Version: 2.1
Name: highrise-bot-sdk
Version: 23.3.4
Summary: The Highrise Bot SDK, for running Highrise bots written in Python.
License: Proprietary
Author: Pocket Worlds Inc
Author-email: server@high.rs
Requires-Python: >=3.10,<4.0
Classifier: License :: Other/Proprietary License
Classifier: Programming Language :: Python :: 3
Classifier: Programming Language :: Python :: 3.10
Classifier: Programming Language :: Python :: 3.11
Requires-Dist: aiohttp (>=3.8.4)
Requires-Dist: cattrs (==22.2.0)
Requires-Dist: click (>=8.1.3)
Requires-Dist: pendulum (>=2.1.2,<3.0.0)
Requires-Dist: quattro (>=22.1.0,<23.0.0)
Requires-Dist: typing_extensions (<4.0.0)
